youcab/__init__.py
youcab/config.py
youcab/errors.py
youcab/word.py
youcab/youcab.py
youcab-0.1.3.dist-info/LICENSE
youcab-0.1.3.dist-info/WHEEL
youcab-0.1.3.dist-info/METADATA
youcab-0.1.3.dist-info/RECORD
