Metadata-Version: 2.1
Name: youcab
Version: 0.1.3
Summary: Converts MeCab parsing results to Python objects.
Home-page: https://github.com/poyo46/youcab
License: BSD-3-Clause
Keywords: mecab,ipadic,unidic,neologd,nlp
Author: poyo46
Author-email: poyo4rock@gmail.com
Requires-Python: >=3.6,<4.0
Classifier: Development Status :: 3 - Alpha
Classifier: Intended Audience :: Developers
Classifier: License :: OSI Approved :: BSD License
Classifier: Natural Language :: Japanese
Classifier: Operating System :: MacOS :: MacOS X
Classifier: Operating System :: POSIX :: Linux
Classifier: Programming Language :: Python :: 3
Classifier: Programming Language :: Python :: 3.6
Classifier: Programming Language :: Python :: 3.7
Classifier: Programming Language :: Python :: 3.8
Classifier: Programming Language :: Python :: 3.9
Classifier: Topic :: Text Processing :: Linguistic
Requires-Dist: mecab-python3 (>=1.0.2,<2.0.0)
Project-URL: Repository, https://github.com/poyo46/youcab
